MANIFEST.in
README.md
setup.py
django_payments_hbl/__init__.py
django_payments_hbl/forms.py
django_payments_hbl.egg-info/PKG-INFO
django_payments_hbl.egg-info/SOURCES.txt
django_payments_hbl.egg-info/dependency_links.txt
django_payments_hbl.egg-info/not-zip-safe
django_payments_hbl.egg-info/top_level.txt
django_payments_hbl/static/js/hbl.js