Metadata-Version: 1.1
Name: django-payments-hbl
Version: 0.1.2
Summary: Himalayan Bank Payment Gateway with django-payments
Home-page: http://github.com/xtranophilist/django-payments-hbl
Author: Awecode
Author-email: dipesh@awecode.com
License: BSD License
Keywords: django,payments,ecommerce,saleor,bank
Platform: UNKNOWN
Classifier: Environment :: Web Environment
Classifier: Framework :: Django
Classifier: Intended Audience :: Developers
Classifier: License :: OSI Approved :: BSD License
Classifier: Operating System :: OS Independent
Classifier: Programming Language :: Python
Classifier: Programming Language :: Python :: 3.4
Classifier: Programming Language :: Python :: 3.5
Classifier: Programming Language :: Python :: 3.6
Classifier: Topic :: Software Development :: Libraries :: Application Frameworks
Classifier: Topic :: Software Development :: Libraries :: Python Modules
